{
  "users": {
    "6283111152212@s.whatsapp.net": {
      "afkTime": -1,
      "banned": false,
      "afkReason": ""
    },
    "6281370040608@s.whatsapp.net": {
      "afkTime": -1,
      "banned": false,
      "afkReason": ""
    },
    "6282122375139@s.whatsapp.net": {
      "afkTime": -1,
      "banned": false,
      "afkReason": ""
    },
    "6287880804639@s.whatsapp.net": {
      "afkTime": -1,
      "banned": false,
      "afkReason": ""
    },
    "628992553934@s.whatsapp.net": {
      "afkTime": -1,
      "banned": false,
      "afkReason": ""
    },
    "6288707795917@s.whatsapp.net": {
      "afkTime": -1,
      "banned": false,
      "afkReason": ""
    },
    "6288976585732@s.whatsapp.net": {
      "afkTime": -1,
      "banned": false,
      "afkReason": ""
    },
    "6288223927112@s.whatsapp.net": {
      "afkTime": -1,
      "banned": false,
      "afkReason": ""
    },
    "6281573008469@s.whatsapp.net": {
      "afkTime": -1,
      "banned": false,
      "afkReason": ""
    },
    "6285773954553@s.whatsapp.net": {
      "afkTime": -1,
      "banned": false,
      "afkReason": ""
    },
    "628993498773@s.whatsapp.net": {
      "afkTime": -1,
      "banned": false,
      "afkReason": ""
    },
    "6289519082134@s.whatsapp.net": {
      "afkTime": -1,
      "banned": false,
      "afkReason": ""
    },
    "6285773040727@s.whatsapp.net": {
      "afkTime": -1,
      "banned": false,
      "afkReason": ""
    },
    "6288210744844@s.whatsapp.net": {
      "afkTime": -1,
      "banned": false,
      "afkReason": ""
    },
    "6281387741882@s.whatsapp.net": {
      "afkTime": -1,
      "banned": false,
      "afkReason": ""
    },
    "6283870151528@s.whatsapp.net": {
      "afkTime": -1,
      "banned": false,
      "afkReason": ""
    },
    "6281779171150@s.whatsapp.net": {
      "afkTime": -1,
      "banned": false,
      "afkReason": ""
    },
    "6281808894731@s.whatsapp.net": {
      "afkTime": -1,
      "banned": false,
      "afkReason": ""
    },
    "6287823360651@s.whatsapp.net": {
      "afkTime": -1,
      "banned": false,
      "afkReason": ""
    },
    "6287823360651:2@s.whatsapp.net": {
      "afkTime": -1,
      "banned": false,
      "afkReason": ""
    },
    "6285714335405@s.whatsapp.net": {
      "afkTime": -1,
      "banned": false,
      "afkReason": ""
    },
    "6285899985209@s.whatsapp.net": {
      "afkTime": -1,
      "banned": false,
      "afkReason": ""
    },
    "6281318870802@s.whatsapp.net": {
      "afkTime": -1,
      "banned": false,
      "afkReason": ""
    },
    "628992553934:30@s.whatsapp.net": {
      "afkTime": -1,
      "banned": false,
      "afkReason": ""
    },
    "628111500620@s.whatsapp.net": {
      "afkTime": -1,
      "banned": false,
      "afkReason": ""
    },
    "6281221512202@s.whatsapp.net": {
      "afkTime": -1,
      "banned": false,
      "afkReason": ""
    },
    "6289630663805@s.whatsapp.net": {
      "afkTime": -1,
      "banned": false,
      "afkReason": ""
    },
    "6283818202506@s.whatsapp.net": {
      "afkTime": -1,
      "banned": false,
      "afkReason": ""
    },
    "6285649472773@s.whatsapp.net": {
      "afkTime": -1,
      "banned": false,
      "afkReason": ""
    },
    "6287798164992@s.whatsapp.net": {
      "afkTime": -1,
      "banned": false,
      "afkReason": ""
    },
    "6285920718194@s.whatsapp.net": {
      "afkTime": -1,
      "banned": false,
      "afkReason": ""
    },
    "6289630663805:6@s.whatsapp.net": {
      "afkTime": -1,
      "banned": false,
      "afkReason": ""
    }
  },
  "chats": {
    "6283111152212@s.whatsapp.net": {
      "mute": false,
      "setWelcome": "",
      "setLeave": ""
    },
    "6281370040608@s.whatsapp.net": {
      "mute": false,
      "setWelcome": "",
      "setLeave": ""
    },
    "120363044497331929@g.us": {
      "mute": false,
      "setWelcome": "",
      "setLeave": "",
      "nsfw": true
    },
    "120363025108004614@g.us": {
      "mute": false,
      "setWelcome": "",
      "setLeave": ""
    },
    "6281318870802@s.whatsapp.net": {
      "mute": false,
      "setWelcome": "",
      "setLeave": ""
    },
    "628111500620@s.whatsapp.net": {
      "mute": false,
      "setWelcome": "",
      "setLeave": ""
    }
  },
  "database": {},
  "game": {
    "math": [],
    "family100": [],
    "tebakgambar": [],
    "tebakkata": [],
    "tebakbendera": [],
    "siapaaku": [],
    "tebakkalimat": [],
    "caklontong": [],
    "susunkata": [],
    "tekateki": [],
    "tebakkabupaten": [],
    "tebakkimia": [],
    "tebaklirik": [],
    "tebaktebakan": []
  },
  "absen": {
    "120363044497331929@g.us": [
      null,
      [
        "6282122375139@s.whatsapp.net"
      ],
      ""
    ]
  },
  "cmd": {},
  "settings": {
    "6283111152212@s.whatsapp.net": {
      "available": false,
      "composing": false,
      "recording": false,
      "autorespond": false
    }
  }
}